{
  "name": "2021-11-07_8778_Artem_Sapegin",
  "slug": "2021-11-07-8778",
  "color": "#687888",
  "width": 1463,
  "height": 2048,
  "modified": "2026-01-29T09:05:44.000Z",
  "timestamp": "2021-11-07T08:26:13.000Z",
  "formattedDate": "November 2021",
  "title": "Morning fog on autumn river",
  "caption": "",
  "location": "Rathen, Germany",
  "keywords": [
    "autumn",
    "dawn",
    "fall",
    "fog",
    "forest",
    "landscape",
    "morning",
    "nature",
    "sunrise",
    "woods"
  ],
  "rating": 5
}